items.py
review.py
glowpick_crawling-0.0.1.dist-info/METADATA
glowpick_crawling-0.0.1.dist-info/WHEEL
glowpick_crawling-0.0.1.dist-info/top_level.txt
glowpick_crawling-0.0.1.dist-info/RECORD
