Metadata-Version: 2.1
Name: glowpick-crawling
Version: 0.0.1
Summary: glowpick web crawling code
Home-page: http://yangjun-ux.github.io
Author: Jin-Kyung Oh, Ye-Seul Yoon, Hee-Jae Lee, Jun Yang
Author-email: nov16jun@gmail.com
License: MIT
Platform: UNKNOWN
Requires-Python: >=3
